{
    "Ar36": {
        "error": 0.0001694595705272133,
        "error_type": "",
        "fit": "previous",
        "references": [
            {
                "exclude": false,
                "record_id": "ba-02-F-470"
            }
        ],
        "value": 0.0021400365769243973
    },
    "Ar37": {
        "error": 0.01334948893116924,
        "error_type": "",
        "fit": "previous",
        "references": [
            {
                "exclude": false,
                "record_id": "ba-02-F-470"
            }
        ],
        "value": 0.03640222435548562
    },
    "Ar38": {
        "error": 0.005065846073251837,
        "error_type": "",
        "fit": "previous",
        "references": [
            {
                "exclude": false,
                "record_id": "ba-02-F-470"
            }
        ],
        "value": 0.015586460427701523
    },
    "Ar39": {
        "error": 0.01220193107933257,
        "error_type": "",
        "fit": "previous",
        "references": [
            {
                "exclude": false,
                "record_id": "ba-02-F-470"
            }
        ],
        "value": 0.002023424011558757
    },
    "Ar40": {
        "error": 0.02643203530135563,
        "error_type": "",
        "fit": "previous",
        "references": [
            {
                "exclude": false,
                "record_id": "ba-02-F-470"
            }
        ],
        "value": 0.13929292201678928
    }
}